Workbook

Sheet Summary
B2: Report Summary
B4: Report Period | C4: 29-December-2025 - 04-January-2026
B5: Res id | C5: GFFBRTDI1750158157
B6: MID | C6: GFF22932
B7: Legal Entity | C7: MANN HOSPITALITY LLP
B8: Res Name | C8: DILLI DARBAR
B9: Address | C9: 166, Mann Food Court, A K Gopalan Colony Main Rd, Ambedkar Nagar, Whitefield, Bengaluru, Karnataka 560066.
B10: PAN
B11: GSTIN | C11: 29ABNFM9601R1Z9
B12: GrowthFalcons GSTIN | C12: 29AAKFH0619N1ZZ
B13: Pay-out cycle | C13: Weekly(Every Wednesday)
B15: Total Orders(Delivered + Cancelled) | C15: =('Payout Breakup'!D4 + 'Payout Breakup'!E4) -> 0
B16: Net Pay-out(Settled) | C16: =('Payout Breakup'!D45) -> 0
B22: Report Detailed Breakdown
B23: This report comprises the following detailed tabs regarding your pay-out:
B24: Pay-out Breakup | C24: Breakup of your total earnings during this report period
B25: Order Level | C25: Detailed view of your order level earnings, deductions, pay-outs for orders.
B26: Daily breakup completed | C26: Detailed view of completed orders summarized for a day
B27: Glossary | C27: Descriptions of the terms used in the Order Level tab

Sheet Payout Breakup
B2: Payout Breakup
B3: S.No. | C3: Particular | D3: Delivered Orders | E3: Cancelled Orders
C4: Number of Orders | D4: =IFERROR(COUNTIF('Order Level'!H:H,"Completed"),0) -> 0 | E4: =IFERROR(COUNTIF('Order Level'!H:H,"Cancelled"),0) -> 0
B5: Column1 | C5: Column2 | D5: Column3 | E5: Column4
B6: A | C6: Net order value [ 1 + 2 + 3 + 4 - 5 - 6 + 7 + 8 + 9] | D6: =D7+D8+D9+D10-D11-D12+D13+D14+D15 -> 0 | E6: 0
B7: 1 | C7: ='Order Level'!N3 -> 0 | D7: =IFERROR(SUMIFS('Order Level'!$N:$N, 'Order Level'!$H:$H, "Completed"),0) -> 0 | E7: 0
B8: 2 | C8: ='Order Level'!O3 -> 0 | D8: =IFERROR(SUMIFS('Order Level'!$O:$O, 'Order Level'!$H:$H, "Completed"),0) -> 0 | E8: 0
B9: 3 | C9: ='Order Level'!P3 -> 0 | D9: =IFERROR(SUMIFS('Order Level'!$P:$P, 'Order Level'!$H:$H, "Completed"),0) -> 0 | E9: 0
B10: 4 | C10: ='Order Level'!Q3 -> 0 | D10: =IFERROR(SUMIFS('Order Level'!$Q:$Q, 'Order Level'!$H:$H, "Completed"),0) -> 0 | E10: 0
B11: 5 | C11: ='Order Level'!R3 -> 0 | D11: =IFERROR(SUMIFS('Order Level'!$R:$R, 'Order Level'!$H:$H, "Completed"),0) -> 0 | E11: 0
B12: 6 | C12: ='Order Level'!S3 -> 0 | D12: =IFERROR(SUMIFS('Order Level'!$S:$S, 'Order Level'!$H:$H, "Completed"),0) -> 0 | E12: 0
B13: 7 | C13: ='Order Level'!T3 -> 0 | D13: =IFERROR(SUMIFS('Order Level'!$T:$T, 'Order Level'!$H:$H, "Completed"),0) -> 0 | E13: 0
B14: 8 | C14: ='Order Level'!U3 -> 0 | D14: =IFERROR(SUMIFS('Order Level'!$U:$U, 'Order Level'!$H:$H, "Completed"),0) -> 0 | E14: 0
B15: 9 | C15: ='Order Level'!V3 -> 0 | D15: =IFERROR(SUMIFS('Order Level'!$V:$V, 'Order Level'!$H:$H, "Completed"),0) -> 0 | E15: 0
B18: 10 | C18: Commissionable value [[ 1 + 2 + 3 + 4 - 5 - 6 + 7 + 8 + 9]] | D18: =SUM(D7:D15) -> 0 | E18: 0
B20: B | C20: Service fees & payment mechanism fees [11 + 12] | D20: =SUM(D21:D23) -> 0 | E20: 0
B21: 11 | C21: =LEFT('Order Level'!Z3, FIND("[", 'Order Level'!Z3) - 2) -> 0 | D21: =IFERROR(SUM('Order Level'!$Z:$Z),0) -> 0 | E21: 0
B22: 12 | C22: =LEFT('Order Level'!AA3, FIND("[", 'Order Level'!AA3) - 2) -> 0 | D22: =IFERROR(SUM('Order Level'!$AA:$AA),0) -> 0 | E22: 0
B25: C | C25: Government Charges [13 + 14 + 15 + 16 ] | D25: =SUM(D26:D29) -> 0 | E25: 0
B26: 13 | C26: =LEFT('Order Level'!AC3, FIND("(", 'Order Level'!AC3) - 2) -> 0 | D26: =IFERROR(SUM('Order Level'!$AC:$AC), 0) -> 0 | E26: 0
B27: 14 | C27: =('Order Level'!AF3 & " + " & 'Order Level'!AG3) -> 0 | D27: =IFERROR(SUMIFS('Order Level'!$AF:$AF,'Order Level'!$H:$H,"Completed") + SUMIFS('Order Level'!$AG:$AG,'Order Level'!$H:$H,"Completed"), 0) -> 0 | E27: 0
B28: 15 | C28: ='Order Level'!AH3 -> 0 | D28: =IFERROR(SUM('Order Level'!$AH:$AH), 0) -> 0 | E28: 0
B29: 16 | C29: GST paid by GrowthFalcons on behalf of restaurant - under section 9(5) | D29: =IFERROR(SUMIFS('Order Level'!$AI:$AI,'Order Level'!$H:$H,"Completed"), 0) -> 0 | E29: 0
B32: D | C32: Other order level deductions [17 + 18 + 19 + 20 + 21] | D32: =SUM(D33:D37) -> 0 | E32: 0
B33: 17 | C33: ='Order Level'!AL3 -> 0 | D33: =IFERROR(SUMIFS('Order Level'!$AL:$AL, 'Order Level'!$H:$H, "Completed"),0) -> 0 | E33: 0
B34: 18 | C34: ='Order Level'!AM3 -> 0 | D34: =IFERROR(SUMIFS('Order Level'!$AM:$AM, 'Order Level'!$H:$H, "Completed"),0) -> 0 | E34: 0
B35: 19 | C35: ='Order Level'!AN3 -> 0 | D35: =IFERROR(SUMIFS('Order Level'!$AN:$AN, 'Order Level'!$H:$H, "Completed"),0) -> 0 | E35: 0
B36: 20 | C36: ='Order Level'!AO3 -> 0 | D36: =IFERROR(SUMIFS('Order Level'!$AO:$AO, 'Order Level'!$H:$H, "Completed"),0) -> 0 | E36: 0
B37: 21 | C37: ='Order Level'!AP3 -> 0 | D37: =IFERROR(SUMIFS('Order Level'!$AP:$AP, 'Order Level'!$H:$H, "Completed"),0) -> 0 | E37: 0
B40: E | C40: Total Additions [ 22 + 23] | D40: =SUM(D41:D42) -> 0 | E40: 0
B41: 22 | C41: Cancellation refund for cancelled Orders | D41: =IFERROR(SUMIFS('Order Level'!$AS:$AS,'Order Level'!$H:$H,"Cancelled"), 0) -> 0 | E41: 0
B42: 23 | C42: Tip for Kitchen Staff for delivered Orders | D42: 0 | E42: 0
B45: F | C45: Net Payout [A - B - C - D + E - A.4 - A.8 ] | D45: =ROUNDDOWN(D6-D20-D25-D32+D40-D10,0) -> 0 | E45: 0

Sheet Order Level
A1: Order level Breakup
N2: (1) | O2: (2) | P2: (3) | Q2: (4) | R2: (5) | S2: (6) | T2: (7) | U2: (8) | V2: (9) | W2: (A) | X2: (10) | Y2: (11) | Z2: (12) | AA2: (13) | AB2: (B) | AC2: (14) | AD2: (15) | AE2: (16) | AF2: (17) | AG2: (18) | AH2: (19) | AI2: (20) | AJ2: (21) | AK2: (C) | AL2: (22) | AM2: (23) | AN2: (24) | AO2: (25) | AP2: (26) | AQ2: (D) | AR2: (E) | AS2: (F) | AT2: (G)
A3: Sl.No | B3: Order ID | C3: Order Date | D3: Restaurant Name | E3: Restaurant ID | F3: Discount Construct | G3: Mode of Payment | H3: Order Status (Delivered/ Cancelled) | I3: Cancellation policy(% Amount refunded back to restaurant partner) | J3: Cancellation/ Rejection Reason | K3: Cancelled/ Rejected State(Order status at the time it was cancelled/ rejected) | L3: Order type | M3: Delivery State code | N3: Subtotal (items total) | O3: Packaging charge | P3: Delivery charge for restaurants on self logistics | Q3: Logistics charge | R3: Restaurant discount [Promo] | S3: Restaurant discount [Flat offs, Freebies, Gold & others] | T3: Brand pack subscription fee | U3: Convenience Fee | V3: Total GST collected from customers | W3: Net Order Value [(1) + (2) + (3) + (4) - (5) - (6) + (7) + (8) + (9)] | X3: Commissionable value [(1) + (2) + (3) + (4) - (5) - (6) + (7) + (8) + (9)] | Y3: Service fees % | Z3: Service fee [ (10) * (11) ] + 15 | AA3: Payment mechanism fee [(10) * (0.018500000000000003) ] | AB3: Service fee & payment mechanism fees [(12) + (13)] | AC3: Taxes on service & payment mechanism fees () (B) * 18% | AD3: Applicable amount for TCS | AE3: Applicable amount for 9(5) | AF3: Tax collected at source | AG3: TCS IGST amount | AH3: TDS 194O amount | AI3: GST paid by GrowthFalcons on behalf of restaurant - under section 9(5) | AJ3: GST to be paid by Restaurant partner to Govt. | AK3: Government charges [(14) + (17) + (18) + (19) + (20)] | AL3: Customer Compensation/Recoupment | AM3: Delivery Charges Recovery | AN3: Credit note/(Debit Note) adjustment | AO3: Promo recovery adjustment | AP3: Extra Inventory Ads and Misc. (order level deduction) | AQ3: Other order-level deductions [(22) + (23) + (24) + (25) + (26) + (27)] | AR3: Net Deductions (B) + (C) + (D) - (4) - (8) | AS3: Net Additions (cancellation refund for cancelled orders/Tip for Kitchen Staff for delivered orders) | AT3: Order level Payout (A) - (E) + (F) | AU3: Buyer App | AV3: Settlement Status | AW3: Settlement Date | AX3: Bank UTR | AY3: Delivery charge discount
A4: 1 | B4: GFFWP10211766999302 | C4: 2025-12-29 | D4: DILLI DARBAR | E4: GFFBRTDI1750158157 | G4: Online | H4: Completed | L4: O2 | N4: 238 | O4: 0 | P4: 0 | Q4: 27 | T4: 0 | U4: 0 | V4: 11.9 | W4: 276.9 | X4: 276.9 | Y4: 0 | Z4: 15 | AA4: 5.12265 | AB4: 20.12265 | AC4: 3.62 | AD4: 0 | AE4: 0 | AF4: 0 | AG4: 0 | AH4: 0.238 | AI4: 11.9 | AJ4: 0 | AK4: 15.758 | AL4: 0 | AM4: 55 | AN4: 0 | AO4: 0 | AP4: 0 | AQ4: 55 | AR4: 117.88065 | AS4: 0 | AT4: 159.02 | AU4: whatsapp | AV4: Settled | AW4: 2026-01-07 | AX4: IN42600858239862 | AY4: 55
A5: 2 | B5: GFFWP99911767080804 | C5: 2025-12-30 | D5: DILLI DARBAR | E5: GFFBRTDI1750158157 | G5: Online | H5: Completed | L5: O2 | N5: 169 | O5: 0 | P5: 0 | Q5: 14 | T5: 0 | U5: 0 | V5: 8.46 | W5: 191.46 | X5: 191.46 | Y5: 0 | Z5: 15 | AA5: 3.54201 | AB5: 18.54201 | AC5: 3.34 | AD5: 0 | AE5: 0 | AF5: 0 | AG5: 0 | AH5: 0.169 | AI5: 8.46 | AJ5: 0 | AK5: 11.969 | AL5: 0 | AM5: 55 | AN5: 0 | AO5: 0 | AP5: 0 | AQ5: 55 | AR5: 99.51101 | AS5: 0 | AT5: 91.95 | AU5: whatsapp | AV5: Settled | AW5: 2026-01-07 | AX5: IN42600858239862 | AY5: 55
A6: 3 | B6: GFFWP16341767102579 | C6: 2025-12-30 | D6: DILLI DARBAR | E6: GFFBRTDI1750158157 | G6: Online | H6: Completed | L6: O2 | N6: 174 | O6: 0 | P6: 0 | Q6: 14 | T6: 0 | U6: 0 | V6: 8.7 | W6: 196.7 | X6: 196.7 | Y6: 0 | Z6: 15 | AA6: 3.63895 | AB6: 18.63895 | AC6: 3.36 | AD6: 0 | AE6: 0 | AF6: 0 | AG6: 0 | AH6: 0.174 | AI6: 8.7 | AJ6: 0 | AK6: 12.234 | AL6: 0 | AM6: 55 | AN6: 0 | AO6: 0 | AP6: 0 | AQ6: 55 | AR6: 99.87295 | AS6: 0 | AT6: 96.83 | AU6: whatsapp | AV6: Settled | AW6: 2026-01-07 | AX6: IN42600858239862 | AY6: 55
A7: 4 | B7: GFFWP05311767186589 | C7: 2025-12-31 | D7: DILLI DARBAR | E7: GFFBRTDI1750158157 | G7: Online | H7: Completed | L7: O2 | N7: 338 | O7: 0 | P7: 0 | Q7: 34 | T7: 0 | U7: 0 | V7: 16.9 | W7: 388.9 | X7: 388.9 | Y7: 0 | Z7: 15 | AA7: 7.19465 | AB7: 22.19465 | AC7: 4 | AD7: 0 | AE7: 0 | AF7: 0 | AG7: 0 | AH7: 0.338 | AI7: 16.9 | AJ7: 0 | AK7: 21.238 | AL7: 0 | AM7: 55 | AN7: 0 | AO7: 0 | AP7: 0 | AQ7: 55 | AR7: 132.43265 | AS7: 0 | AT7: 256.47 | AU7: whatsapp | AV7: Settled | AW7: 2026-01-07 | AX7: IN42600858239862 | AY7: 55
A8: 5 | B8: GFFWP66511767191397 | C8: 2025-12-31 | D8: DILLI DARBAR | E8: GFFBRTDI1750158157 | G8: Online | H8: Completed | L8: O2 | N8: 371 | O8: 0 | P8: 0 | Q8: 34 | T8: 0 | U8: 0 | V8: 18.56 | W8: 423.56 | X8: 423.56 | Y8: 0 | Z8: 15 | AA8: 7.83586 | AB8: 22.83586 | AC8: 4.11 | AD8: 0 | AE8: 0 | AF8: 0 | AG8: 0 | AH8: 0.371 | AI8: 18.56 | AJ8: 0 | AK8: 23.041 | AL8: 0 | AM8: 55 | AN8: 0 | AO8: 0 | AP8: 0 | AQ8: 55 | AR8: 134.87686 | AS8: 0 | AT8: 288.68 | AU8: whatsapp | AV8: Settled | AW8: 2026-01-07 | AX8: IN42600858239862 | AY8: 55
A9: 6 | B9: GFFWP83191767195560 | C9: 2025-12-31 | D9: DILLI DARBAR | E9: GFFBRTDI1750158157 | G9: Online | H9: Completed | L9: O2 | N9: 243 | O9: 0 | P9: 0 | Q9: 34 | T9: 0 | U9: 0 | V9: 12.16 | W9: 289.16 | X9: 289.16 | Y9: 0 | Z9: 15 | AA9: 5.34946 | AB9: 20.34946 | AC9: 3.66 | AD9: 0 | AE9: 0 | AF9: 0 | AG9: 0 | AH9: 0.243 | AI9: 12.16 | AJ9: 0 | AK9: 16.063 | AL9: 0 | AM9: 55 | AN9: 0 | AO9: 0 | AP9: 0 | AQ9: 55 | AR9: 125.41246 | AS9: 0 | AT9: 163.74 | AU9: whatsapp | AV9: Settled | AW9: 2026-01-07 | AX9: IN42600858239862 | AY9: 55
A10: 7 | B10: GFFWP95961767252653 | C10: 2026-01-01 | D10: DILLI DARBAR | E10: GFFBRTDI1750158157 | G10: Online | H10: Completed | L10: O2 | N10: 149 | O10: 0 | P10: 0 | Q10: 34 | T10: 0 | U10: 0 | V10: 7.46 | W10: 190.46 | X10: 190.46 | Y10: 0 | Z10: 15 | AA10: 3.52351 | AB10: 18.52351 | AC10: 3.33 | AD10: 0 | AE10: 0 | AF10: 0 | AG10: 0 | AH10: 0.149 | AI10: 7.46 | AJ10: 0 | AK10: 10.939 | AL10: 0 | AM10: 55 | AN10: 0 | AO10: 0 | AP10: 0 | AQ10: 55 | AR10: 118.46251 | AS10: 0 | AT10: 71.99 | AU10: whatsapp | AV10: Settled | AW10: 2026-01-07 | AX10: IN42600858239862 | AY10: 55
A11: 8 | B11: GFFWP99911767253872 | C11: 2026-01-01 | D11: DILLI DARBAR | E11: GFFBRTDI1750158157 | G11: Online | H11: Completed | L11: O2 | N11: 189 | O11: 0 | P11: 0 | Q11: 34 | T11: 0 | U11: 0 | V11: 9.46 | W11: 232.46 | X11: 232.46 | Y11: 0 | Z11: 15 | AA11: 4.30051 | AB11: 19.30051 | AC11: 3.47 | AD11: 0 | AE11: 0 | AF11: 0 | AG11: 0 | AH11: 0.189 | AI11: 9.46 | AJ11: 0 | AK11: 13.119 | AL11: 0 | AM11: 55 | AN11: 0 | AO11: 0 | AP11: 0 | AQ11: 55 | AR11: 121.41951 | AS11: 0 | AT11: 111.04 | AU11: whatsapp | AV11: Settled | AW11: 2026-01-07 | AX11: IN42600858239862 | AY11: 55
A12: 9 | B12: GFFWP83191767255717 | C12: 2026-01-01 | D12: DILLI DARBAR | E12: GFFBRTDI1750158157 | G12: Online | H12: Completed | L12: O2 | N12: 149 | O12: 0 | P12: 0 | Q12: 34 | T12: 0 | U12: 0 | V12: 7.46 | W12: 190.46 | X12: 190.46 | Y12: 0 | Z12: 15 | AA12: 3.52351 | AB12: 18.52351 | AC12: 3.33 | AD12: 0 | AE12: 0 | AF12: 0 | AG12: 0 | AH12: 0.149 | AI12: 7.46 | AJ12: 0 | AK12: 10.939 | AL12: 0 | AM12: 55 | AN12: 0 | AO12: 0 | AP12: 0 | AQ12: 55 | AR12: 118.46251 | AS12: 0 | AT12: 71.99 | AU12: whatsapp | AV12: Settled | AW12: 2026-01-07 | AX12: IN42600858239862 | AY12: 55
A13: 10 | B13: GFFWP27661767262822 | C13: 2026-01-01 | D13: DILLI DARBAR | E13: GFFBRTDI1750158157 | G13: Online | H13: Completed | L13: O2 | N13: 298 | O13: 0 | P13: 0 | Q13: 34 | T13: 0 | U13: 0 | V13: 14.92 | W13: 346.92 | X13: 346.92 | Y13: 0 | Z13: 15 | AA13: 6.41802 | AB13: 21.41802 | AC13: 3.86 | AD13: 0 | AE13: 0 | AF13: 0 | AG13: 0 | AH13: 0.298 | AI13: 14.92 | AJ13: 0 | AK13: 19.078 | AL13: 0 | AM13: 55 | AN13: 0 | AO13: 0 | AP13: 0 | AQ13: 55 | AR13: 129.49602 | AS13: 0 | AT13: 217.43 | AU13: whatsapp | AV13: Settled | AW13: 2026-01-07 | AX13: IN42600858239862 | AY13: 55
A14: 11 | B14: GFFWP99911767270262 | C14: 2026-01-01 | D14: DILLI DARBAR | E14: GFFBRTDI1750158157 | G14: Online | H14: Completed | L14: O2 | N14: 594 | O14: 0 | P14: 0 | Q14: 34 | T14: 0 | U14: 0 | V14: 29.72 | W14: 657.72 | X14: 657.72 | Y14: 0 | Z14: 15 | AA14: 12.16782 | AB14: 27.16782 | AC14: 4.89 | AD14: 0 | AE14: 0 | AF14: 0 | AG14: 0 | AH14: 0.594 | AI14: 29.72 | AJ14: 0 | AK14: 35.204 | AL14: 0 | AM14: 55 | AN14: 0 | AO14: 0 | AP14: 0 | AQ14: 55 | AR14: 151.37182 | AS14: 0 | AT14: 506.35 | AU14: whatsapp | AV14: Settled | AW14: 2026-01-07 | AX14: IN42600858239862 | AY14: 55
A15: 12 | B15: GFFWP00971767278075 | C15: 2026-01-01 | D15: DILLI DARBAR | E15: GFFBRTDI1750158157 | G15: Online | H15: Completed | L15: O2 | N15: 869 | O15: 0 | P15: 0 | Q15: 34 | T15: 0 | U15: 0 | V15: 43.48 | W15: 946.48 | X15: 946.48 | Y15: 0 | Z15: 15 | AA15: 17.50988 | AB15: 32.50988 | AC15: 5.85 | AD15: 0 | AE15: 0 | AF15: 0 | AG15: 0 | AH15: 0.869 | AI15: 43.48 | AJ15: 0 | AK15: 50.199 | AL15: 0 | AM15: 55 | AN15: 0 | AO15: 0 | AP15: 0 | AQ15: 55 | AR15: 171.70888 | AS15: 0 | AT15: 774.77 | AU15: whatsapp | AV15: Settled | AW15: 2026-01-07 | AX15: IN42600858239862 | AY15: 55
... A28: 25 | B28: GFFWP83191767545412 | C28: 2026-01-04 | D28: DILLI DARBAR | E28: GFFBRTDI1750158157 | G28: Online | H28: Completed | L28: O2 | N28: 497 | O28: 0 | P28: 0 | Q28: 14 | T28: 0 | U28: 0 | V28: 24.86 | W28: 535.86 | X28: 535.86 | Y28: 0 | Z28: 15 | AA28: 9.91341 | AB28: 24.91341 | AC28: 4.48 | AD28: 0 | AE28: 0 | AF28: 0 | AG28: 0 | AH28: 0.497 | AI28: 24.86 | AJ28: 0 | AK28: 29.837 | AL28: 0 | AM28: 55 | AN28: 0 | AO28: 0 | AP28: 0 | AQ28: 55 | AR28: 123.75041 | AS28: 0 | AT28: 412.11 | AU28: whatsapp | AV28: Settled | AW28: 2026-01-07 | AX28: IN42600858239862 | AY28: 55

Sheet Daywise Completed Breakup
A1: Daywise Breakup for Completed Orders
A2: Order Date | B2: Number of Orders | C2: Net Order Value | D2: Copay Amount | E2: Subtotal (items total) | F2: Total Packaging Charge | G2: Total GST | H2: Service fee % | I2: Taxes on Service Fee % | J2: TDS | K2: Service Fee | L2: Taxes on Service Fee | M2: Self Delivery Charges | N2: Delivery Discount | O2: Total Payable to Merchant
A3: 2025-12-29 | B3: 1 | C3: 276.9 | D3: 0 | E3: 238 | F3: 0 | G3: 11.9 | I3: 18% | J3: 0.238 | K3: 15 | L3: 2.7 | M3: 0 | N3: 55 | O3: 159.02
A4: 2025-12-30 | B4: 2 | C4: 388.16 | D4: 0 | E4: 343 | F4: 0 | G4: 17.16 | I4: 18% | J4: 0.343 | K4: 30 | L4: 5.4 | M4: 0 | N4: 110 | O4: 188.78
A5: 2025-12-31 | B5: 3 | C5: 1101.62 | D5: 0 | E5: 952 | F5: 0 | G5: 47.62 | I5: 18% | J5: 0.952 | K5: 45 | L5: 8.1 | M5: 0 | N5: 165 | O5: 708.89
A6: 2026-01-01 | B6: 7 | C6: 2833.7 | D6: 0 | E6: 2472 | F6: 0 | G6: 123.7 | I6: 18% | J6: 2.472 | K6: 105 | L6: 18.9 | M6: 0 | N6: 385 | O6: 1898.77
A7: 2026-01-02 | B7: 2 | C7: 431.62 | D7: 0 | E7: 372 | F7: 0 | G7: 18.62 | I7: 18% | J7: 0.372 | K7: 30 | L7: 5.4 | M7: 0 | N7: 110 | O7: 216.81
A8: 2026-01-03 | B8: 4 | C8: 1146.86 | D8: 0 | E8: 1026.5 | F8: 0 | G8: 51.36 | I8: 18% | J8: 1.0265 | K8: 60 | L8: 10.8 | M8: 0 | N8: 220 | O8: 709.64
A9: 2026-01-04 | B9: 6 | C9: 1860.62 | D9: 0 | E9: 1692 | F9: 0 | G9: 84.62 | I9: 18% | J9: 1.692 | K9: 90 | L9: 16.2 | M9: 0 | N9: 330 | O9: 1213.5

Sheet Glossary
A1: Glossary
A2: Descriptions of the terms used in the Order level tab
A3: S.No | B3: Particulars | C3: Definition
A4: 1 | B4: Subtotal (items total) | C4: Gross total of dishes/items ordered by the customer before discount
A5: 2 | B5: Packaging charge | C5: Cost set by the restaurant partner for the packaging material of whatever nature, including containers and coverings
A6: 3 | B6: Delivery charge for restaurants on self logistics | C6: Cost charged by restaurant partner when the delivery of order is undertaken by the restaurant partner themselves
A7: 4 | B7: Logistics Charge | C7: Cost charged for using delivery services from GrowthFalcons Platform
A8: 5 | B8: Restaurant Discount [Promo] | C8: Offer or Promo discounts borne by the restaurant partner on the order
A9: 6 | B9: Restaurant discount [Flat offs, Freebies, Gold & others] | C9: PRO/SALT/ Freebie or any other discounts borne by the restaurant partner on the order
A10: 7 | B10: Brand pack subscription fee | C10: Revenue generated for the restaurant through brand pack subscriptions
A11: 8 | B11: Convenience fee | C11: Fee charged by GrowthFalcons to customer for providing service
A12: 9 | B12: Total GST collected from customers | C12: Total tax amount paid by the customer on the order. It include GST on Food items, Packaging charges and delivery charges (for orders delivered by the restaurant partners themselves) after adjusting restaurant partner discount
A13: 10 | B13: Net order value | C13: This means the subtotal value received, including the packaging charge, Delivery Charge (for orders delivered by the restaurant partners themselves) and less restaurant partner discounts
A14: 11 | B14: Commissionable value (excluding customer GST) | C14: It is amount at which GrowthFalcons commission will be applied i.e. the total of Gross sales less delivery Charge (for orders delivered by restaurant partners themselves) and taxes
A15: 12 | B15: Service fee % | C15: This means the amount payable by the Restaurant Partner to GrowthFalcons, being a % of commissionable value
... A37: 34 | B37: Order level Payout | C37: Net transferable amount after all deductions
